prfr/__init__.py
prfr/model.py
prfr/utils.py
prfr-0.2.4.dist-info/LICENSE
prfr-0.2.4.dist-info/WHEEL
prfr-0.2.4.dist-info/METADATA
prfr-0.2.4.dist-info/RECORD
