Metadata-Version: 2.1
Name: prfr
Version: 0.2.4
Summary: Probabilitic random forest regression algorithm
Home-page: https://github.com/al-jshen/prfr
License: MIT
Keywords: machine learning,random forest,regression,probabilistic,modeling
Author: Jeff Shen
Author-email: shenjeff@princeton.edu
Requires-Python: >=3.8,<4.0
Classifier: Development Status :: 3 - Alpha
Classifier: Intended Audience :: Science/Research
Classifier: License :: OSI Approved :: MIT License
Classifier: Natural Language :: English
Classifier: Operating System :: OS Independent
Classifier: Programming Language :: Python :: 3
Classifier: Programming Language :: Python :: 3.8
Classifier: Programming Language :: Python :: 3.9
Classifier: Programming Language :: Python :: 3.10
Classifier: Programming Language :: Python :: 3.11
Classifier: Topic :: Scientific/Engineering
Provides-Extra: jax
Requires-Dist: jax (>=0.3.24,<0.4.0); extra == "jax"
Requires-Dist: jaxopt (>=0.5.5,<0.6.0); extra == "jax"
Requires-Dist: joblib (>=1.1.0,<2.0.0)
Requires-Dist: noisyopt (>=0.2.2,<0.3.0)
Requires-Dist: numpy (>=1.21,<2.0)
Requires-Dist: optax (>=0.1.3,<0.2.0); extra == "jax"
Requires-Dist: scikit-learn (>=1.1,<2.0)
Requires-Dist: scipy (>=1.8.0,<2.0.0)
Requires-Dist: tqdm (>=4.64.0,<5.0.0)
Project-URL: Repository, https://github.com/al-jshen/prfr
